s3pathx/__init__.py
s3pathx/helper.py
s3pathx-0.1.0.dist-info/LICENSE
s3pathx-0.1.0.dist-info/METADATA
s3pathx-0.1.0.dist-info/WHEEL
s3pathx-0.1.0.dist-info/top_level.txt
s3pathx-0.1.0.dist-info/RECORD
