Metadata-Version: 2.2
Name: s3pathx
Version: 0.1.0
Summary: Lightweight S3 utility class with pathlib-style API
Home-page: https://github.com/hotwa/s3helper
Author: hotwa
Author-email: Your Name <your@email.com>
License: MIT
Project-URL: Homepage, https://github.com/yourusername/s3helper
Project-URL: Bug_Tracker, https://github.com/yourusername/s3helper/issues
Requires-Python: >=3.8
License-File: LICENSE
Requires-Dist: boto3
